.gitignore
LICENSE
README.md
setup.cfg
setup.py
hanlp_downloader/__init__.py
hanlp_downloader/bin.py
hanlp_downloader/chunk.py
hanlp_downloader/down.py
hanlp_downloader/log.py
hanlp_downloader/term.py
hanlp_downloader.egg-info/PKG-INFO
hanlp_downloader.egg-info/SOURCES.txt
hanlp_downloader.egg-info/dependency_links.txt
hanlp_downloader.egg-info/requires.txt
hanlp_downloader.egg-info/top_level.txt
tests/__init__.py
tests/api_test.py
tests/bin_test.py
tests/download_file.py
tests/download_small_file.py