Metadata-Version: 1.0
Name: hanlp-downloader
Version: 0.0.25
Summary: A tool and library to save large files by creating multiple connections, modified from pget by Halil Ozercan.
Home-page: UNKNOWN
Author: UNKNOWN
Author-email: UNKNOWN
License: UNKNOWN
Platform: UNKNOWN
